commons_cli/__init__.py
commons_cli/cli.py
commons_cli/main.py
commons_cli-0.1.2.dist-info/METADATA
commons_cli-0.1.2.dist-info/WHEEL
commons_cli-0.1.2.dist-info/entry_points.txt
commons_cli-0.1.2.dist-info/top_level.txt
commons_cli-0.1.2.dist-info/RECORD
