Metadata-Version: 2.4
Name: commons-cli
Version: 0.1.2
Summary: Terminal-based chat client for Commons with real-time messaging
Author: Commons Project
License: MIT
Project-URL: Homepage, https://github.com/commons-project/commons
Project-URL: Repository, https://github.com/commons-project/commons
Project-URL: Issues, https://github.com/commons-project/commons/issues
Keywords: chat,tui,terminal,websocket,cli
Classifier: Development Status :: 3 - Alpha
Classifier: Environment :: Console :: Curses
Classifier: Intended Audience :: End Users/Desktop
Classifier: License :: OSI Approved :: MIT License
Classifier: Operating System :: POSIX :: Linux
Classifier: Operating System :: Microsoft :: Windows
Classifier: Operating System :: MacOS
Classifier: Programming Language :: Python :: 3
Classifier: Programming Language :: Python :: 3.7
Classifier: Programming Language :: Python :: 3.8
Classifier: Programming Language :: Python :: 3.9
Classifier: Programming Language :: Python :: 3.10
Classifier: Programming Language :: Python :: 3.11
Classifier: Programming Language :: Python :: 3.12
Classifier: Topic :: Communications :: Chat
Classifier: Topic :: Terminals
Requires-Python: >=3.7
Requires-Dist: requests>=2.31.0
Requires-Dist: websocket-client>=1.6.0
Requires-Dist: windows-curses>=2.3.0; sys_platform == "win32"
